setuptools_behave.py
behave/__init__.py
behave/__main__.py
behave/_stepimport.py
behave/_types.py
behave/capture.py
behave/configuration.py
behave/fixture.py
behave/i18n.py
behave/importer.py
behave/json_parser.py
behave/log_capture.py
behave/matchers.py
behave/model.py
behave/model_core.py
behave/model_describe.py
behave/parser.py
behave/runner.py
behave/runner_util.py
behave/step_registry.py
behave/tag_expression.py
behave/tag_matcher.py
behave/textutil.py
behave/userdata.py
behave/api/__init__.py
behave/api/async_step.py
behave/compat/__init__.py
behave/compat/collections.py
behave/contrib/__init__.py
behave/contrib/formatter_missing_steps.py
behave/contrib/scenario_autoretry.py
behave/contrib/substep_dirs.py
behave/formatter/__init__.py
behave/formatter/_builtins.py
behave/formatter/_registry.py
behave/formatter/ansi_escapes.py
behave/formatter/base.py
behave/formatter/formatters.py
behave/formatter/json.py
behave/formatter/null.py
behave/formatter/plain.py
behave/formatter/pretty.py
behave/formatter/progress.py
behave/formatter/rerun.py
behave/formatter/sphinx_steps.py
behave/formatter/sphinx_util.py
behave/formatter/steps.py
behave/formatter/tags.py
behave/reporter/__init__.py
behave/reporter/base.py
behave/reporter/junit.py
behave/reporter/summary.py
behave_plus-0.0.4.dist-info/LICENSE
behave_plus-0.0.4.dist-info/METADATA
behave_plus-0.0.4.dist-info/WHEEL
behave_plus-0.0.4.dist-info/entry_points.txt
behave_plus-0.0.4.dist-info/top_level.txt
behave_plus-0.0.4.dist-info/zip-safe
behave_plus-0.0.4.dist-info/RECORD
