Metadata-Version: 2.1
Name: behave_plus
Version: 0.0.4
Summary: this project update behave with job_language parameter, and behave is behaviour-driven development, Python style
Home-page: http://github.com/behave/behave
Author: yong chen
Author-email: ayongcydew@163.com
License: BSD
Classifier: Development Status :: 4 - Beta
Classifier: Environment :: Console
Classifier: Intended Audience :: Developers
Classifier: Operating System :: OS Independent
Classifier: Programming Language :: Python :: 2
Classifier: Programming Language :: Python :: 2.6
Classifier: Programming Language :: Python :: 2.7
Classifier: Programming Language :: Python :: 3
Classifier: Programming Language :: Python :: 3.3
Classifier: Programming Language :: Python :: 3.4
Classifier: Programming Language :: Python :: 3.5
Classifier: Programming Language :: Python :: 3.6
Classifier: Programming Language :: Python :: Implementation :: CPython
Classifier: Programming Language :: Python :: Implementation :: Jython
Classifier: Programming Language :: Python :: Implementation :: PyPy
Classifier: Topic :: Software Development :: Testing
Classifier: License :: OSI Approved :: BSD License
Provides: behave
Provides: setuptools_behave
Requires-Python: >=2.6, !=3.0.*, !=3.1.*, !=3.2.*
License-File: LICENSE
Requires-Dist: parse >=1.8.2
Requires-Dist: parse-type >=0.4.2
Requires-Dist: six >=1.11
Requires-Dist: argparse ; python_version < "2.7"
Requires-Dist: importlib ; python_version < "2.7"
Requires-Dist: ordereddict ; python_version < "2.7"
Requires-Dist: traceback2 ; python_version < "3.0"
Requires-Dist: enum34 ; python_version < "3.4"
Provides-Extra: develop
Requires-Dist: coverage ; extra == 'develop'
Requires-Dist: pytest >=3.0 ; extra == 'develop'
Requires-Dist: pytest-cov ; extra == 'develop'
Requires-Dist: tox ; extra == 'develop'
Requires-Dist: invoke >=0.21.0 ; extra == 'develop'
Requires-Dist: path.py >=8.1.2 ; extra == 'develop'
Requires-Dist: pycmd ; extra == 'develop'
Requires-Dist: pathlib ; extra == 'develop'
Requires-Dist: modernize >=0.5 ; extra == 'develop'
Requires-Dist: pylint ; extra == 'develop'
Provides-Extra: docs
Requires-Dist: sphinx >=1.6 ; extra == 'docs'
Requires-Dist: sphinx-bootstrap-theme >=0.6 ; extra == 'docs'
